{
    "patches": [
        {
            "label": "2025-10-04_22-54-50",
            "content": "@@ -150,16 +150,18 @@\n  int = 0\n+  \n %0A       \n@@ -184,16 +184,18 @@\n  = False\n+  \n %0A%0A    de\n@@ -1494,44 +1494,4 @@\n d())\n-%0A%0A%0Aif __name__ == %22__main__%22:%0A    main()\n",
            "lines": "65"
        },
        {
            "label": "2025-10-04_22-57-44",
            "content": "@@ -0,0 +1,1533 @@\n+class Animal:%0A    def __init__(self, species: str, sound: str):%0A        self.species: str = species%0A        self.sound: str = sound%0A        self.age: int = 0%0A        self.dead: bool = False%0A%0A    def __str__(self) -%3E str:%0A        return f%22%7Bself.species%7D:%7Bself.age%7D:%7Bself.sound%7D%22%0A%0A    def ageBy(self, increment: int) -%3E None:%0A        if self.dead:%0A            print(f%22warning: %7Bself.species%7D morreu%22)%0A            return%0A%0A        self.age += increment%0A%0A        if self.age %3E 3:%0A            self.age = 4%0A            self.dead = True%0A            print(f%22warning: %7Bself.species%7D morreu%22)%0A%0A    def makeSound(self) -%3E str:%0A        if self.dead:%0A            return %22RIP%22%0A        elif self.age == 0:%0A            return %22---%22%0A        else:%0A            return self.sound%0A%0A%0Adef main():%0A    animal = None%0A%0A    while True:%0A        try:%0A            line = input().strip()%0A        except EOFError:%0A            break%0A%0A        if not line:%0A            continue%0A%0A        parts = line.split()%0A        cmd = parts%5B0%5D%0A%0A        print(f%22$%7Bline%7D%22)%0A%0A        if cmd == %22end%22:%0A            break%0A%0A        elif cmd == %22init%22:%0A            species = parts%5B1%5D%0A            sound = parts%5B2%5D%0A            animal = Animal(species, sound)%0A%0A        elif cmd == %22show%22 and animal is not None:%0A            print(animal)%0A%0A        elif cmd == %22grow%22 and animal is not None:%0A            increment = int(parts%5B1%5D)%0A            animal.ageBy(increment)%0A%0A        elif cmd == %22noise%22 and animal is not None:%0A            print(animal.makeSound())%0A%0A%0Aif __name__ == %22__main__%22:%0A    main()\n",
            "lines": "69"
        },
        {
            "label": "2025-10-04_22-59-52",
            "content": "@@ -1,1650 +0,0 @@\n-class Animal:%0A    def __init__(self, species: str, sound: str):%0A        self.species: str = species%0A        self.sound: str = sound%0A        self.age: int = 0%0A        self.dead: bool = False%0A%0A    def __srt__(self) -%3E str:%0A        return f%22%7Bself.species%7D:%7Bself.age%7D:%7Bself.sound%7D%22%0A%0A    def ageBy(self, increment: int) -%3E Nome:%0A        if self.dead:%0A            print(f%22warning: %7Bself.species%7D morreu foi com Deus%22)%0A            return%0A%0A        self.age += increment%0A%0A        if self.age %3E 3:%0A            self.age = 4%0A            self.dead = True%0A            print(f%22warning: %7Bself.species%7D morreu%22)%0A%0A    def makeSound(self)  -%3E str:%0A        if self.dead:%0A            return %22RIP%22%0A        elif self.age == 0:%0A            return %22---%22%0A        else:%0A            return self.sound%0A    def main():%0A        animal = Nome%0A%0A        while True:%0A            try:%0A                line = input().strip()%0A            except E0Frror:%0A                break%0A            if not line:%0A                continue%0A%0A            parts = line.split()%0A            cmd = parts%5B0%5D%0A%0A            print(f%22$%7Bline%7D%22)%0A%0A            if cmd == %22end%22:%0A                break%0A            %0A            elif cmd == %22init%22:%0A                species = parts%5B1%5D%0A                soud = parts%5B2%5D%0A                animal = Animal(species, sound)%0A%0A            elif cmd == %22show%22 and animal is not Nome:%0A                print(animal)%0A%0A            elif cmd == %22grow%22 and animal is not Nome:%0A                increment = int(parts%5B1%5D)%0A                animal.ageBy(increment)%0A%0A            elif cmd == %22noise%22 and animal is not Nome:%0A                print(aimal.makeSound())%0A%0A%0Aif __name__%22__main___%22:%0A    main()\n",
            "lines": "0"
        },
        {
            "label": "2025-10-04_23-43-07",
            "content": "@@ -1629,16 +1629,17 @@\n __main__\n+_\n %22:%0A    m\n",
            "lines": "66"
        },
        {
            "label": "2025-10-04_23-49-31",
            "content": "@@ -1609,19 +1609,16 @@\n nd())%0A%0A%0A\n-   \n if __nam\n@@ -1624,21 +1624,17 @@\n me__\n- == '\n+%22\n __main__\n ':%0A \n@@ -1633,12 +1633,11 @@\n in__\n-'\n+%22\n :%0A\n- \n     \n@@ -1642,14 +1642,8 @@\n   main()\n-%0A     \n",
            "lines": "66"
        },
        {
            "label": "2025-10-04_23-59-27",
            "content": "@@ -1651,8 +1651,13 @@\n  main()%0A\n+     \n",
            "lines": "67"
        },
        {
            "label": "2025-10-05_00-02-51",
            "content": "@@ -1646,12 +1646,13 @@\n %0A     main()\n+%0A\n",
            "lines": "66"
        },
        {
            "label": "2025-10-05_00-41-45",
            "content": "@@ -1609,16 +1609,19 @@\n nd())%0A%0A%0A\n+   \n if __nam\n@@ -1639,16 +1639,17 @@\n ain__':%0A\n+ \n     main\n",
            "lines": "66"
        },
        {
            "label": "2025-10-05_00-47-05",
            "content": "@@ -195,18 +195,18 @@\n  def __s\n-t\n r\n+t\n __(self)\n@@ -313,17 +313,17 @@\n t) -%3E No\n-n\n+m\n e:%0A     \n@@ -608,24 +608,25 @@\n eSound(self)\n+ \n  -%3E str:%0A   \n@@ -766,18 +766,20 @@\n f.sound%0A\n-%0A%0A\n+    \n def main\n@@ -782,16 +782,20 @@\n main():%0A\n+    \n     anim\n@@ -805,12 +805,16 @@\n = No\n-n\n+m\n e%0A%0A\n+    \n     \n@@ -825,16 +825,41 @@\n e True:%0A\n+            try:%0A        \n         \n@@ -881,16 +881,70 @@\n strip()%0A\n+            except E0Frror:%0A                break%0A    \n         \n@@ -968,16 +968,20 @@\n         \n+   \n+ \n continue\n@@ -982,16 +982,20 @@\n ntinue%0A%0A\n+    \n         \n@@ -1023,16 +1023,20 @@\n         \n+ \n+   \n cmd = pa\n@@ -1043,16 +1043,20 @@\n rts%5B0%5D%0A%0A\n+    \n         \n@@ -1070,24 +1070,28 @@\n %22$%7Bline%7D%22)%0A%0A\n+    \n         if c\n@@ -1119,15 +1119,35 @@\n     \n+    \n break%0A\n-%0A\n+            %0A    \n     \n@@ -1182,16 +1182,20 @@\n         \n+   \n+ \n species \n@@ -1217,20 +1217,23 @@\n         \n+    \n sou\n-n\n d = part\n@@ -1241,32 +1241,36 @@\n %5B2%5D%0A            \n+    \n animal = Animal(\n@@ -1286,32 +1286,36 @@\n sound)%0A%0A        \n+  \n+  \n elif cmd == %22sho\n@@ -1329,33 +1329,33 @@\n animal is not No\n-n\n+m\n e:%0A            p\n@@ -1345,32 +1345,36 @@\n me:%0A            \n+  \n+  \n print(animal)%0A%0A \n@@ -1372,32 +1372,36 @@\n nimal)%0A%0A        \n+   \n+ \n elif cmd == %22gro\n@@ -1415,33 +1415,33 @@\n animal is not No\n-n\n+m\n e:%0A            i\n@@ -1439,16 +1439,20 @@\n         \n+   \n+ \n incremen\n@@ -1469,16 +1469,20 @@\n rts%5B1%5D)%0A\n+    \n         \n@@ -1510,32 +1510,36 @@\n ement)%0A%0A        \n+    \n elif cmd == %22noi\n@@ -1562,20 +1562,24 @@\n s not No\n-n\n+m\n e:%0A\n+    \n         \n@@ -1585,25 +1585,24 @@\n      print(a\n-n\n imal.makeSou\n",
            "lines": "66"
        },
        {
            "label": "2025-10-05_00-49-11",
            "content": "@@ -389,16 +389,29 @@\n %7D morreu\n+ foi com Deus\n %22)%0A     \n",
            "lines": "65"
        },
        {
            "label": "2025-10-05_00-50-03",
            "content": "class Animal:\n    def __init__(self, species: str, sound: str):\n        self.species: str = species\n        self.sound: str = sound\n        self.age: int = 0\n        self.dead: bool = False\n\n    def __str__(self) -> str:\n        return f\"{self.species}:{self.age}:{self.sound}\"\n\n    def ageBy(self, increment: int) -> None:\n        if self.dead:\n            print(f\"warning: {self.species} morreu\")\n            return\n\n        self.age += increment\n\n        if self.age > 3:\n            self.age = 4\n            self.dead = True\n            print(f\"warning: {self.species} morreu\")\n\n    def makeSound(self) -> str:\n        if self.dead:\n            return \"RIP\"\n        elif self.age == 0:\n            return \"---\"\n        else:\n            return self.sound\n\n\ndef main():\n    animal = None\n\n    while True:\n        line = input().strip()\n        if not line:\n            continue\n\n        parts = line.split()\n        cmd = parts[0]\n\n        print(f\"${line}\")\n\n        if cmd == \"end\":\n            break\n\n        elif cmd == \"init\":\n            species = parts[1]\n            sound = parts[2]\n            animal = Animal(species, sound)\n\n        elif cmd == \"show\" and animal is not None:\n            print(animal)\n\n        elif cmd == \"grow\" and animal is not None:\n            increment = int(parts[1])\n            animal.ageBy(increment)\n\n        elif cmd == \"noise\" and animal is not None:\n            print(animal.makeSound())\n\n\nif __name__ == '__main__':\n    main()",
            "lines": "65"
        }
    ]
}